{
  "_class": "shapePath",
  "booleanOperation": -1,
  "clippingMaskMode": 0,
  "do_objectID": "AA33CA5E-DC20-47D0-8F7B-BFAC1FFF15D0",
  "edited": true,
  "exportOptions": {
    "_class": "exportOptions",
    "exportFormats": [
    ],
    "includedLayerIds": [
    ],
    "layerOptions": 0,
    "shouldTrim": false
  },
  "frame": {
    "_class": "rect",
    "constrainProportions": false,
    "height": 12.34799999999996,
    "width": 10.05682706104631,
    "x": 0.09503841170976557,
    "y": 0.06899999999995998
  },
  "hasClippingMask": true,
  "isClosed": true,
  "isFixedToViewport": false,
  "isFlippedHorizontal": false,
  "isFlippedVertical": false,
  "isLocked": false,
  "isVisible": true,
  "layerListExpandedType": 0,
  "name": "Clip 137",
  "nameIsFixed": false,
  "pointRadiusBehaviour": 1,
  "points": [
    {
      "_class": "curvePoint",
      "cornerRadius": 0,
      "curveFrom": "{0.10420399813271068, 0.073777129899583849}",
      "curveMode": 4,
      "curveTo": "{0.16535648651367574, 0.044136702299973657}",
      "hasCurveFrom": true,
      "hasCurveTo": false,
      "point": "{0.16535648651367574, 0.044136702299973657}"
    },
    {
      "_class": "curvePoint",
      "cornerRadius": 0,
      "curveFrom": "{0.03310801570606945, 0.16075477810170935}",
      "curveMode": 4,
      "curveTo": "{0.060253754450781259, 0.11248785228376265}",
      "hasCurveFrom": false,
      "hasCurveTo": true,
      "point": "{0.03310801570606945, 0.16075477810170935}"
    },
    {
      "_class": "curvePoint",
      "cornerRadius": 0,
      "curveFrom": "{0.0053656673186080316, 0.20885973436993521}",
      "curveMode": 4,
      "curveTo": "{0.03310801570606945, 0.16075477810170935}",
      "hasCurveFrom": true,
      "hasCurveTo": false,
      "point": "{0.03310801570606945, 0.16075477810170935}"
    },
    {
      "_class": "curvePoint",
      "cornerRadius": 0,
      "curveFrom": "{0.0019848793430645643, 0.3157596371882006}",
      "curveMode": 4,
      "curveTo": "{-0.0046772616675452607, 0.26093294460641331}",
      "hasCurveFrom": false,
      "hasCurveTo": true,
      "point": "{0.0019848793430645643, 0.3157596371882006}"
    },
    {
      "_class": "curvePoint",
      "cornerRadius": 0,
      "curveFrom": "{0.0033769685094727953, 0.32466796242306678}",
      "curveMode": 4,
      "curveTo": "{0.0019848793430645643, 0.3157596371882006}",
      "hasCurveFrom": true,
      "hasCurveTo": false,
      "point": "{0.0019848793430645643, 0.3157596371882006}"
    },
    {
      "_class": "curvePoint",
      "cornerRadius": 0,
      "curveFrom": "{0.015607466185647718, 0.33689666342728347}",
      "curveMode": 4,
      "curveTo": "{0.0078515408300157737, 0.33130871396176781}",
      "hasCurveFrom": false,
      "hasCurveTo": true,
      "point": "{0.015607466185647718, 0.33689666342728347}"
    },
    {
      "_class": "curvePoint",
      "cornerRadius": 0,
      "curveFrom": "{0.023462826481756772, 0.34280855199222238}",
      "curveMode": 4,
      "curveTo": "{0.015607466185647718, 0.33689666342728347}",
      "hasCurveFrom": true,
      "hasCurveTo": false,
      "point": "{0.015607466185647718, 0.33689666342728347}"
    },
    {
      "_class": "curvePoint",
      "cornerRadius": 0,
      "curveFrom": "{0.042852639870836637, 0.34564301911241047}",
      "curveMode": 4,
      "curveTo": "{0.032511406063319835, 0.34564301911241047}",
      "hasCurveFrom": false,
      "hasCurveTo": true,
      "point": "{0.042852639870836637, 0.34564301911241047}"
    },
    {
      "_class": "curvePoint",
      "cornerRadius": 0,
      "curveFrom": "{0.042852639870836637, 0.34564301911241047}",
      "curveMode": 1,
      "curveTo": "{0.042852639870836637, 0.34564301911241047}",
      "hasCurveFrom": false,
      "hasCurveTo": false,
      "point": "{0.042852639870836637, 0.34564301911241047}"
    },
    {
      "_class": "curvePoint",
      "cornerRadius": 0,
      "curveFrom": "{0.20990333983835477, 0.34564301911241047}",
      "curveMode": 4,
      "curveTo": "{0.19866719156672485, 0.34564301911241047}",
      "hasCurveFrom": true,
      "hasCurveTo": false,
      "point": "{0.19866719156672485, 0.34564301911241047}"
    },
    {
      "_class": "curvePoint",
      "cornerRadius": 0,
      "curveFrom": "{0.22899484840604853, 0.337706511175906}",
      "curveMode": 4,
      "curveTo": "{0.22004570376493995, 0.34280855199222238}",
      "hasCurveFrom": false,
      "hasCurveTo": true,
      "point": "{0.22899484840604853, 0.337706511175906}"
    },
    {
      "_class": "curvePoint",
      "cornerRadius": 0,
      "curveFrom": "{0.2379439930471797, 0.33260447035957125}",
      "curveMode": 4,
      "curveTo": "{0.22899484840604853, 0.337706511175906}",
      "hasCurveFrom": true,
      "hasCurveTo": false,
      "point": "{0.22899484840604853, 0.337706511175906}"
    },
    {
      "_class": "curvePoint",
      "cornerRadius": 0,
      "curveFrom": "{0.24480500393869853, 0.31316812439261221}",
      "curveMode": 4,
      "curveTo": "{0.24361178465322189, 0.32466796242306678}",
      "hasCurveFrom": false,
      "hasCurveTo": true,
      "point": "{0.24480500393869853, 0.31316812439261221}"
    },
    {
      "_class": "curvePoint",
      "cornerRadius": 0,
      "curveFrom": "{0.24569991840281163, 0.26935536119209863}",
      "curveMode": 4,
      "curveTo": "{0.24480500393869853, 0.31316812439261221}",
      "hasCurveFrom": true,
      "hasCurveTo": false,
      "point": "{0.24480500393869853, 0.31316812439261221}"
    },
    {
      "_class": "curvePoint",
      "cornerRadius": 0,
      "curveFrom": "{0.28865581268017343, 0.20586329770002634}",
      "curveMode": 4,
      "curveTo": "{0.26041628959041691, 0.23339812115322903}",
      "hasCurveFrom": false,
      "hasCurveTo": true,
      "point": "{0.28865581268017343, 0.20586329770002634}"
    },
    {
      "_class": "curvePoint",
      "cornerRadius": 0,
      "curveFrom": "{0.31689533576990736, 0.17808551992226085}",
      "curveMode": 4,
      "curveTo": "{0.28865581268017343, 0.20586329770002634}",
      "hasCurveFrom": true,
      "hasCurveTo": false,
      "point": "{0.28865581268017343, 0.20586329770002634}"
    },
    {
      "_class": "curvePoint",
      "cornerRadius": 0,
      "curveFrom": "{0.41762293045271337, 0.16431810819565951}",
      "curveMode": 4,
      "curveTo": "{0.36024896980910981, 0.16431810819565951}",
      "hasCurveFrom": false,
      "hasCurveTo": true,
      "point": "{0.41762293045271337, 0.16431810819565951}"
    },
    {
      "_class": "curvePoint",
      "cornerRadius": 0,
      "curveFrom": "{0.47658785014361155, 0.16431810819565951}",
      "curveMode": 4,
      "curveTo": "{0.41762293045271337, 0.16431810819565951}",
      "hasCurveFrom": true,
      "hasCurveTo": false,
      "point": "{0.41762293045271337, 0.16431810819565951}"
    },
    {
      "_class": "curvePoint",
      "cornerRadius": 0,
      "curveFrom": "{0.55484314828315773, 0.20205701328149495}",
      "curveMode": 4,
      "curveTo": "{0.52212905287285827, 0.17703271784903868}",
      "hasCurveFrom": false,
      "hasCurveTo": true,
      "point": "{0.55484314828315773, 0.20205701328149495}"
    },
    {
      "_class": "curvePoint",
      "cornerRadius": 0,
      "curveFrom": "{0.58765667863393434, 0.22756721736313212}",
      "curveMode": 4,
      "curveTo": "{0.55484314828315773, 0.20205701328149495}",
      "hasCurveFrom": true,
      "hasCurveTo": false,
      "point": "{0.55484314828315773, 0.20205701328149495}"
    },
    {
      "_class": "curvePoint",
      "cornerRadius": 0,
      "curveFrom": "{0.61480241737864616, 0.30612244897959073}",
      "curveMode": 4,
      "curveTo": "{0.60764310166576385, 0.26222870100421669}",
      "hasCurveFrom": false,
      "hasCurveTo": true,
      "point": "{0.61480241737864616, 0.30612244897959073}"
    },
    {
      "_class": "curvePoint",
      "cornerRadius": 0,
      "curveFrom": "{0.61897868487782559, 0.33341431810819372}",
      "curveMode": 4,
      "curveTo": "{0.61480241737864616, 0.30612244897959073}",
      "hasCurveFrom": true,
      "hasCurveTo": false,
      "point": "{0.61480241737864616, 0.30612244897959073}"
    },
    {
      "_class": "curvePoint",
      "cornerRadius": 0,
      "curveFrom": "{0.5953131690491118, 0.38896987366376157}",
      "curveMode": 4,
      "curveTo": "{0.61271428362905644, 0.36062520246193636}",
      "hasCurveFrom": false,
      "hasCurveTo": true,
      "point": "{0.5953131690491118, 0.38896987366376157}"
    },
    {
      "_class": "curvePoint",
      "cornerRadius": 0,
      "curveFrom": "{0.57830979423098516, 0.41707159054098714}",
      "curveMode": 4,
      "curveTo": "{0.5953131690491118, 0.38896987366376157}",
      "hasCurveFrom": true,
      "hasCurveTo": false,
      "point": "{0.5953131690491118, 0.38896987366376157}"
    },
    {
      "_class": "curvePoint",
      "cornerRadius": 0,
      "curveFrom": "{0.51119120942261442, 0.48104956268222188}",
      "curveMode": 4,
      "curveTo": "{0.55016970608168314, 0.44768383543894069}",
      "hasCurveFrom": false,
      "hasCurveTo": true,
      "point": "{0.51119120942261442, 0.48104956268222188}"
    },
    {
      "_class": "curvePoint",
      "cornerRadius": 0,
      "curveFrom": "{0.47211327782306861, 0.51441528992550301}",
      "curveMode": 4,
      "curveTo": "{0.51119120942261442, 0.48104956268222188}",
      "hasCurveFrom": true,
      "hasCurveTo": false,
      "point": "{0.51119120942261442, 0.48104956268222188}"
    },
    {
      "_class": "curvePoint",
      "cornerRadius": 0,
      "curveFrom": "{0.34284785522916517, 0.60957240038873262}",
      "curveMode": 4,
      "curveTo": "{0.4158331015244871, 0.55709426627793401}",
      "hasCurveFrom": false,
      "hasCurveTo": true,
      "point": "{0.34284785522916517, 0.60957240038873262}"
    },
    {
      "_class": "curvePoint",
      "cornerRadius": 0,
      "curveFrom": "{0.34284785522916517, 0.60957240038873262}",
      "curveMode": 1,
      "curveTo": "{0.34284785522916517, 0.60957240038873262}",
      "hasCurveFrom": false,
      "hasCurveTo": false,
      "point": "{0.34284785522916517, 0.60957240038873262}"
    },
    {
      "_class": "curvePoint",
      "cornerRadius": 0,
      "curveFrom": "{0.083024355815404585, 0.84499514091350869}",
      "curveMode": 4,
      "curveTo": "{0.10877800539373077, 0.82717849044379477}",
      "hasCurveFrom": true,
      "hasCurveTo": false,
      "point": "{0.10877800539373077, 0.82717849044379477}"
    },
    {
      "_class": "curvePoint",
      "cornerRadius": 0,
      "curveFrom": "{0.076262779864340255, 0.89293812763201375}",
      "curveMode": 4,
      "curveTo": "{0.072086512365138175, 0.86686103012633531}",
      "hasCurveFrom": false,
      "hasCurveTo": true,
      "point": "{0.076262779864340255, 0.89293812763201375}"
    },
    {
      "_class": "curvePoint",
      "cornerRadius": 0,
      "curveFrom": "{0.076262779864340255, 0.89293812763201375}",
      "curveMode": 1,
      "curveTo": "{0.076262779864340255, 0.89293812763201375}",
      "hasCurveFrom": false,
      "hasCurveTo": false,
      "point": "{0.076262779864340255, 0.89293812763201375}"
    },
    {
      "_class": "curvePoint",
      "cornerRadius": 0,
      "curveFrom": "{0.089885366706923417, 0.97529964366698541}",
      "curveMode": 4,
      "curveTo": "{0.08849327754053779, 0.96606737933269593}",
      "hasCurveFrom": true,
      "hasCurveTo": false,
      "point": "{0.08849327754053779, 0.96606737933269593}"
    },
    {
      "_class": "curvePoint",
      "cornerRadius": 0,
      "curveFrom": "{0.10380625837089268, 0.99003887269193003}",
      "curveMode": 4,
      "curveTo": "{0.095155418551147619, 0.98372206025267073}",
      "hasCurveFrom": false,
      "hasCurveTo": true,
      "point": "{0.10380625837089268, 0.99003887269193003}"
    },
    {
      "_class": "curvePoint",
      "cornerRadius": 0,
      "curveFrom": "{0.11295427289291024, 0.99667962423064949}",
      "curveMode": 4,
      "curveTo": "{0.10380625837089268, 0.99003887269193003}",
      "hasCurveFrom": true,
      "hasCurveTo": false,
      "point": "{0.10380625837089268, 0.99003887269193003}"
    },
    {
      "_class": "curvePoint",
      "cornerRadius": 0,
      "curveFrom": "{0.13502882967432947, 1}",
      "curveMode": 4,
      "curveTo": "{0.12339494164088154, 1}",
      "hasCurveFrom": false,
      "hasCurveTo": true,
      "point": "{0.13502882967432947, 1}"
    },
    {
      "_class": "curvePoint",
      "cornerRadius": 0,
      "curveFrom": "{0.13502882967432947, 1}",
      "curveMode": 1,
      "curveTo": "{0.13502882967432947, 1}",
      "hasCurveFrom": false,
      "hasCurveTo": false,
      "point": "{0.13502882967432947, 1}"
    },
    {
      "_class": "curvePoint",
      "cornerRadius": 0,
      "curveFrom": "{0.97475690183244046, 1}",
      "curveMode": 4,
      "curveTo": "{0.96192979451351601, 1}",
      "hasCurveFrom": true,
      "hasCurveTo": false,
      "point": "{0.96192979451351601, 1}"
    },
    {
      "_class": "curvePoint",
      "cornerRadius": 0,
      "curveFrom": "{0.99156140676965809, 0.99076773566569221}",
      "curveMode": 4,
      "curveTo": "{0.98440209105677579, 0.9970035633300911}",
      "hasCurveFrom": false,
      "hasCurveTo": true,
      "point": "{0.99156140676965809, 0.99076773566569221}"
    },
    {
      "_class": "curvePoint",
      "cornerRadius": 0,
      "curveFrom": "{0.99822354778026801, 0.98469387755103244}",
      "curveMode": 4,
      "curveTo": "{0.99156140676965809, 0.99076773566569221}",
      "hasCurveFrom": true,
      "hasCurveTo": false,
      "point": "{0.99156140676965809, 0.99076773566569221}"
    },
    {
      "_class": "curvePoint",
      "cornerRadius": 0,
      "curveFrom": "{0.99961563694665356, 0.96606737933269593}",
      "curveMode": 4,
      "curveTo": "{1.0011071610535163, 0.97627146096534712}",
      "hasCurveFrom": false,
      "hasCurveTo": true,
      "point": "{0.99961563694665356, 0.96606737933269593}"
    },
    {
      "_class": "curvePoint",
      "cornerRadius": 0,
      "curveFrom": "{0.99961563694665356, 0.96606737933269593}",
      "curveMode": 1,
      "curveTo": "{0.99961563694665356, 0.96606737933269593}",
      "hasCurveFrom": false,
      "hasCurveTo": false,
      "point": "{0.99961563694665356, 0.96606737933269593}"
    },
    {
      "_class": "curvePoint",
      "cornerRadius": 0,
      "curveFrom": "{0.98122017296214137, 0.85487528344671826}",
      "curveMode": 4,
      "curveTo": "{0.98340774165220823, 0.86540330417881106}",
      "hasCurveFrom": true,
      "hasCurveTo": false,
      "point": "{0.98340774165220823, 0.86540330417881106}"
    },
    {
      "_class": "curvePoint",
      "cornerRadius": 0,
      "curveFrom": "{0.96710041141726311, 0.83956916099773227}",
      "curveMode": 4,
      "curveTo": "{0.97624842593930328, 0.84645286686103294}",
      "hasCurveFrom": false,
      "hasCurveTo": true,
      "point": "{0.96710041141726311, 0.83956916099773227}"
    },
    {
      "_class": "curvePoint",
      "cornerRadius": 0,
      "curveFrom": "{0.95785296195479097, 0.83349530288305418}",
      "curveMode": 4,
      "curveTo": "{0.96710041141726311, 0.83956916099773227}",
      "hasCurveFrom": true,
      "hasCurveTo": false,
      "point": "{0.96710041141726311, 0.83956916099773227}"
    },
    {
      "_class": "curvePoint",
      "cornerRadius": 0,
      "curveFrom": "{0.93408801118560003, 0.82993197278912245}",
      "curveMode": 4,
      "curveTo": "{0.94701455344497909, 0.82993197278912245}",
      "hasCurveFrom": false,
      "hasCurveTo": true,
      "point": "{0.93408801118560003, 0.82993197278912245}"
    },
    {
      "_class": "curvePoint",
      "cornerRadius": 0,
      "curveFrom": "{0.93408801118560003, 0.82993197278912245}",
      "curveMode": 1,
      "curveTo": "{0.93408801118560003, 0.82993197278912245}",
      "hasCurveFrom": false,
      "hasCurveTo": false,
      "point": "{0.93408801118560003, 0.82993197278912245}"
    },
    {
      "_class": "curvePoint",
      "cornerRadius": 0,
      "curveFrom": "{0.4457630186019928, 0.82993197278912245}",
      "curveMode": 1,
      "curveTo": "{0.4457630186019928, 0.82993197278912245}",
      "hasCurveFrom": false,
      "hasCurveTo": false,
      "point": "{0.4457630186019928, 0.82993197278912245}"
    },
    {
      "_class": "curvePoint",
      "cornerRadius": 0,
      "curveFrom": "{0.73521813027189553, 0.57393909944930466}",
      "curveMode": 4,
      "curveTo": "{0.65368147909728302, 0.63200518302560049}",
      "hasCurveFrom": true,
      "hasCurveTo": false,
      "point": "{0.65368147909728302, 0.63200518302560049}"
    },
    {
      "_class": "curvePoint",
      "cornerRadius": 0,
      "curveFrom": "{0.82828923453950143, 0.46833495302882427}",
      "curveMode": 4,
      "curveTo": "{0.79338757043915775, 0.51935536119209857}",
      "hasCurveFrom": false,
      "hasCurveTo": true,
      "point": "{0.82828923453950143, 0.46833495302882427}"
    },
    {
      "_class": "curvePoint",
      "cornerRadius": 0,
      "curveFrom": "{0.86299202875895886, 0.41731454486556835}",
      "curveMode": 4,
      "curveTo": "{0.82828923453950143, 0.46833495302882427}",
      "hasCurveFrom": true,
      "hasCurveTo": false,
      "point": "{0.82828923453950143, 0.46833495302882427}"
    },
    {
      "_class": "curvePoint",
      "cornerRadius": 0,
      "curveFrom": "{0.86557733721082109, 0.29761904761904501}",
      "curveMode": 4,
      "curveTo": "{0.87562026619697431, 0.36038224813735514}",
      "hasCurveFrom": false,
      "hasCurveTo": true,
      "point": "{0.86557733721082109, 0.29761904761904501}"
    },
    {
      "_class": "curvePoint",
      "cornerRadius": 0,
      "curveFrom": "{0.85652875762925795, 0.24076773566569218}",
      "curveMode": 4,
      "curveTo": "{0.86557733721082109, 0.29761904761904501}",
      "hasCurveFrom": true,
      "hasCurveTo": false,
      "point": "{0.86557733721082109, 0.29761904761904501}"
    },
    {
      "_class": "curvePoint",
      "cornerRadius": 0,
      "curveFrom": "{0.79239322103459009, 0.14463880790411926}",
      "curveMode": 4,
      "curveTo": "{0.83186889239595396, 0.18950437317783661}",
      "hasCurveFrom": false,
      "hasCurveTo": true,
      "point": "{0.79239322103459009, 0.14463880790411926}"
    },
    {
      "_class": "curvePoint",
      "cornerRadius": 0,
      "curveFrom": "{0.75281811473274918, 0.09977324263038348}",
      "curveMode": 4,
      "curveTo": "{0.79239322103459009, 0.14463880790411926}",
      "hasCurveFrom": true,
      "hasCurveTo": false,
      "point": "{0.79239322103459009, 0.14463880790411926}"
    },
    {
      "_class": "curvePoint",
      "cornerRadius": 0,
      "curveFrom": "{0.63021483314945559, 0.038548752834476389}",
      "curveMode": 4,
      "curveTo": "{0.69882494206468904, 0.064301911240694787}",
      "hasCurveFrom": false,
      "hasCurveTo": true,
      "point": "{0.63021483314945559, 0.038548752834476389}"
    },
    {
      "_class": "curvePoint",
      "cornerRadius": 0,
      "curveFrom": "{0.56180359411515368, 0.01279559442823958}",
      "curveMode": 4,
      "curveTo": "{0.63021483314945559, 0.038548752834476389}",
      "hasCurveFrom": true,
      "hasCurveTo": false,
      "point": "{0.63021483314945559, 0.038548752834476389}"
    },
    {
      "_class": "curvePoint",
      "cornerRadius": 0,
      "curveFrom": "{0.38928397242250234, 0}",
      "curveMode": 4,
      "curveTo": "{0.48146016222601778, 0}",
      "hasCurveFrom": false,
      "hasCurveTo": true,
      "point": "{0.38928397242250234, 0}"
    },
    {
      "_class": "curvePoint",
      "cornerRadius": 0,
      "curveFrom": "{0.30098574529682548, 0}",
      "curveMode": 4,
      "curveTo": "{0.38928397242250234, 0}",
      "hasCurveFrom": true,
      "hasCurveTo": false,
      "point": "{0.38928397242250234, 0}"
    },
    {
      "_class": "curvePoint",
      "cornerRadius": 0,
      "curveFrom": "{0.16535648651367574, 0.044136702299973657}",
      "curveMode": 4,
      "curveTo": "{0.22621067007327728, 0.014820213799805099}",
      "hasCurveFrom": false,
      "hasCurveTo": true,
      "point": "{0.16535648651367574, 0.044136702299973657}"
    }
  ],
  "resizingConstraint": 63,
  "resizingType": 0,
  "rotation": 0,
  "shouldBreakMaskChain": false,
  "style": {
    "_class": "style",
    "endMarkerType": 0,
    "miterLimit": 10,
    "startMarkerType": 0,
    "windingRule": 1
  }
}