{
  "_class": "group",
  "booleanOperation": -1,
  "clippingMaskMode": 0,
  "do_objectID": "CF0869E2-CC76-4E71-A214-1E0FDA68702F",
  "exportOptions": {
    "_class": "exportOptions",
    "do_objectID": "FA03F062-76AA-4984-A7E3-B7CD28110E1C",
    "exportFormats": [
    ],
    "includedLayerIds": [
    ],
    "layerOptions": 0,
    "shouldTrim": false
  },
  "frame": {
    "_class": "rect",
    "constrainProportions": false,
    "do_objectID": "7D4261CB-B962-4309-9D6E-7483D81134F8",
    "height": 63,
    "width": 234,
    "x": 0,
    "y": 103
  },
  "groupLayout": {
    "_class": "MSImmutableFreeformGroupLayout",
    "do_objectID": "C9A379AB-99AC-482F-A61D-D4ABB581D507"
  },
  "hasClickThrough": false,
  "hasClippingMask": false,
  "isFixedToViewport": false,
  "isFlippedHorizontal": false,
  "isFlippedVertical": false,
  "isLocked": false,
  "isVisible": true,
  "layerListExpandedType": 0,
  "layers": [
    {
      "class": "symbolInstance",
      "id": "7A4A3917-B58F-4F47-A526-2A41123B24D2"
    },
    {
      "class": "text",
      "id": "DECFAAE5-59AD-489D-88F5-7F07A5A3CA1E"
    },
    {
      "class": "text",
      "id": "C7A0E1A7-CB50-46FE-9903-E1155A90BEA3"
    }
  ],
  "name": "Group 8",
  "nameIsFixed": false,
  "resizingConstraint": 63,
  "resizingType": 0,
  "rotation": 0,
  "shouldBreakMaskChain": false,
  "style": {
    "_class": "style",
    "do_objectID": "3DCE5323-E4F8-4D1E-8F8C-F64E9C5042AE",
    "endMarkerType": 0,
    "miterLimit": 10,
    "startMarkerType": 0,
    "windingRule": 1
  }
}