{
  "_class": "symbolInstance",
  "booleanOperation": -1,
  "clippingMaskMode": 0,
  "do_objectID": "F0B7253B-B7EF-42E7-B106-BC4A756AC3FA",
  "exportOptions": {
    "_class": "exportOptions",
    "do_objectID": "7456071B-B4C0-4F9E-ABF8-4879829D9682",
    "exportFormats": [
    ],
    "includedLayerIds": [
    ],
    "layerOptions": 0,
    "shouldTrim": false
  },
  "frame": {
    "_class": "rect",
    "constrainProportions": false,
    "do_objectID": "851F1829-64CD-49B8-A852-A8B989892B16",
    "height": 138,
    "width": 480,
    "x": 0,
    "y": 594
  },
  "hasClippingMask": false,
  "horizontalSpacing": 0,
  "isFixedToViewport": false,
  "isFlippedHorizontal": false,
  "isFlippedVertical": false,
  "isLocked": false,
  "isVisible": true,
  "layerListExpandedType": 0,
  "name": "cards/staff",
  "nameIsFixed": false,
  "overrideValues": [
    {
      "_class": "overrideValue",
      "overrideName": "C6273549-945D-456C-BA64-AACA8C9D37D7_stringValue",
      "value": "Jamie Williamson"
    },
    {
      "_class": "overrideValue",
      "overrideName": "B2F10281-0A55-4A82-9662-25594F9A446F_stringValue",
      "value": "Teaching Assistant"
    },
    {
      "_class": "overrideValue",
      "overrideName": "DF33D9B2-FF63-4F02-B996-ACF05BE5DCAC_stringValue",
      "value": "jwilliamson@coastalmontessoricharter.org"
    }
  ],
  "resizingConstraint": 63,
  "resizingType": 0,
  "rotation": 0,
  "scale": 1,
  "shouldBreakMaskChain": false,
  "style": {
    "_class": "style",
    "do_objectID": "E9FAAC48-3755-4FA6-A796-CB8484A3BE5A",
    "endMarkerType": 0,
    "miterLimit": 10,
    "startMarkerType": 0,
    "windingRule": 1
  },
  "symbolID": "CB064EC4-5BA5-482F-9B14-B9B1E6043A62",
  "verticalSpacing": 0
}